cli_acetone.py
cli_compare.py
code_generator/Layer.py
code_generator/activation_functions.py
code_generator/neural_network.py
code_generator/layers/AddBiase.py
code_generator/layers/Concatenate.py
code_generator/layers/Dense.py
code_generator/layers/Dot.py
code_generator/layers/Gather.py
code_generator/layers/Gemm.py
code_generator/layers/Input.py
code_generator/layers/MatMul.py
code_generator/layers/Softmax.py
code_generator/layers/Broadcast_layers/Add.py
code_generator/layers/Broadcast_layers/Average.py
code_generator/layers/Broadcast_layers/Broadcast.py
code_generator/layers/Broadcast_layers/Divide.py
code_generator/layers/Broadcast_layers/Maximum.py
code_generator/layers/Broadcast_layers/Minimum.py
code_generator/layers/Broadcast_layers/Multiply.py
code_generator/layers/Broadcast_layers/Subtract.py
code_generator/layers/Conv_layers/Conv2D.py
code_generator/layers/Conv_layers/Conv2D_6loops.py
code_generator/layers/Conv_layers/Conv2D_gemm.py
code_generator/layers/Conv_layers/Conv2D_indirect_gemm.py
code_generator/layers/Conv_layers/Conv2D_std_gemm.py
code_generator/layers/Pad_layers/ConstantPad.py
code_generator/layers/Pad_layers/EdgePad.py
code_generator/layers/Pad_layers/Pad.py
code_generator/layers/Pad_layers/ReflectPad.py
code_generator/layers/Pad_layers/WrapPad.py
code_generator/layers/Pooling_layers/AveragePooling2D.py
code_generator/layers/Pooling_layers/MaxPooling2D.py
code_generator/layers/Pooling_layers/Pooling2D.py
code_generator/layers/Resize_layers/Resize.py
code_generator/layers/Resize_layers/ResizeCubic.py
code_generator/layers/Resize_layers/ResizeLinear.py
code_generator/layers/Resize_layers/ResizeNearest.py
format_importer/parser.py
format_importer/H5_importer/JSON_from_keras_model.py
format_importer/JSON_importer/parser_JSON.py
format_importer/NNET_importer/nnet_normalize.py
format_importer/NNET_importer/parser_NNET.py
format_importer/ONNX_importer/create_layer.py
format_importer/ONNX_importer/parser_ONNX.py
graph/graph_interpretor.py
acetone_neuralnet-0.0.1.dist-info/AUTHORS.md
acetone_neuralnet-0.0.1.dist-info/COPYING
acetone_neuralnet-0.0.1.dist-info/LICENSE
acetone_neuralnet-0.0.1.dist-info/METADATA
acetone_neuralnet-0.0.1.dist-info/WHEEL
acetone_neuralnet-0.0.1.dist-info/entry_points.txt
acetone_neuralnet-0.0.1.dist-info/top_level.txt
acetone_neuralnet-0.0.1.dist-info/RECORD
