Metadata-Version: 2.1
Name: acetone-neuralnet
Version: 0.0.1
Summary: Predictable programming framework for ML applications in safety-critical systems.
Author-email: Iryna DE ALBUQUERQUE SILVA <Iryna.De_Albuquerque_Silva@onera.fr>, Thomas CARLE <Thomas.Carle@irit.fr>, Adrien GAUFFRIAU <Adrien.Gauffriau@airbus.com>, Claire PAGETTI <Claire.Pagetti@onera.fr>
Project-URL: Repository, https://github.com/onera/acetone/
Project-URL: Bug Tracker, https://github.com/onera/acetone/issues
Classifier: Development Status :: 3 - Alpha
Classifier: Programming Language :: Python :: 3
Classifier: Programming Language :: C
Classifier: License :: OSI Approved :: GNU Lesser General Public License v3 (LGPLv3)
Classifier: Operating System :: OS Independent
Classifier: Intended Audience :: Science/Research
Classifier: Topic :: Software Development :: Code Generators
Classifier: Topic :: Software Development :: Embedded Systems
Classifier: Topic :: Scientific/Engineering :: Artificial Intelligence
Requires-Python: >=3.10
License-File: LICENSE
License-File: COPYING
License-File: AUTHORS.md
Requires-Dist: numpy ==1.23.5
Requires-Dist: numpyencoder ==0.3.0
Requires-Dist: onnx ==1.14.0
Requires-Dist: tensorflow ==2.12.0
Requires-Dist: pystache ==0.6.5
